{"commitInfo":{"timestamp":1784746312114,"operation":"WRITE","operationParameters":{"partitionBy":"[\"gender\"]","mode":"Overwrite"},"engineInfo":"delta-rs:py-1.6.2","operationMetrics":{"execution_time_ms":15,"num_added_files":2,"num_added_rows":3,"num_partitions":0,"num_removed_files":0},"clientVersion":"delta-rs.py-1.6.2"}}
{"protocol":{"minReaderVersion":1,"minWriterVersion":2}}
{"metaData":{"id":"9b6ada7c-0d06-486c-b682-2dd16bcc2edc","name":null,"description":null,"format":{"provider":"parquet","options":{}},"schemaString":"{\"type\":\"struct\",\"fields\":[{\"name\":\"patient_id\",\"type\":\"string\",\"nullable\":true,\"metadata\":{}},{\"name\":\"name\",\"type\":\"string\",\"nullable\":true,\"metadata\":{}},{\"name\":\"email\",\"type\":\"string\",\"nullable\":true,\"metadata\":{}},{\"name\":\"dob\",\"type\":\"date\",\"nullable\":true,\"metadata\":{}},{\"name\":\"gender\",\"type\":\"string\",\"nullable\":true,\"metadata\":{}},{\"name\":\"created_at\",\"type\":\"string\",\"nullable\":true,\"metadata\":{}},{\"name\":\"_ingestion_time\",\"type\":\"string\",\"nullable\":true,\"metadata\":{}},{\"name\":\"_source_system\",\"type\":\"string\",\"nullable\":true,\"metadata\":{}}]}","partitionColumns":["gender"],"createdTime":1784746312098,"configuration":{}}}
{"add":{"path":"gender=Female/part-00000-91bc386c-7a79-49c5-9d6a-389adb6caebd-c000.snappy.parquet","partitionValues":{"gender":"Female"},"size":2441,"modificationTime":1784746312113,"dataChange":true,"stats":"{\"numRecords\":1,\"minValues\":{\"_source_system\":\"source_api\",\"patient_id\":\"P102\",\"name\":\"Jane Smith\",\"dob\":\"1992-11-22\",\"created_at\":\"2026-07-16T12:05:00Z\",\"email\":\"jane@example.co\",\"_ingestion_time\":\"2026-07-22T18:51:51.656972+00:00\"},\"maxValues\":{\"email\":\"jane@example.co\",\"_source_system\":\"source_api\",\"name\":\"Jane Smith\",\"patient_id\":\"P102\",\"dob\":\"1992-11-22\",\"created_at\":\"2026-07-16T12:05:00Z\",\"_ingestion_time\":\"2026-07-22T18:51:51.656972+00:00\"},\"nullCount\":{\"dob\":0,\"_ingestion_time\":0,\"_source_system\":0,\"email\":0,\"created_at\":0,\"patient_id\":0,\"name\":0}}","tags":null,"baseRowId":null,"defaultRowCommitVersion":null,"clusteringProvider":null}}
{"add":{"path":"gender=Male/part-00000-e8128b23-e736-4d86-96a6-6ef4981d41b1-c000.snappy.parquet","partitionValues":{"gender":"Male"},"size":2497,"modificationTime":1784746312113,"dataChange":true,"stats":"{\"numRecords\":2,\"minValues\":{\"dob\":\"1975-02-09\",\"_source_system\":\"source_api\",\"email\":\"bob-invalid\",\"name\":\"Bob Johnson\",\"created_at\":\"2026-07-16T12:00:00Z\",\"_ingestion_time\":\"2026-07-22T18:51:51.656972+00:00\",\"patient_id\":\"P101\"},\"maxValues\":{\"created_at\":\"2026-07-16T12:10:00Z\",\"name\":\"John Doe\",\"email\":\"john@example.com\",\"patient_id\":\"P103\",\"_ingestion_time\":\"2026-07-22T18:51:51.656972+00:00\",\"_source_system\":\"source_api\",\"dob\":\"1980-05-15\"},\"nullCount\":{\"patient_id\":0,\"email\":0,\"dob\":0,\"created_at\":0,\"_source_system\":0,\"_ingestion_time\":0,\"name\":0}}","tags":null,"baseRowId":null,"defaultRowCommitVersion":null,"clusteringProvider":null}}