{"commitInfo":{"timestamp":1784315152415,"operation":"WRITE","operationParameters":{"mode":"Overwrite"},"engineInfo":"delta-rs:py-1.6.2","operationMetrics":{"execution_time_ms":2,"num_added_files":1,"num_added_rows":2,"num_partitions":0,"num_removed_files":0},"clientVersion":"delta-rs.py-1.6.2"}}
{"protocol":{"minReaderVersion":3,"minWriterVersion":7,"readerFeatures":["timestampNtz"],"writerFeatures":["timestampNtz"]}}
{"metaData":{"id":"71090771-7db6-4a5a-8ab7-5fb8312b3297","name":null,"description":null,"format":{"provider":"parquet","options":{}},"schemaString":"{\"type\":\"struct\",\"fields\":[{\"name\":\"gender\",\"type\":\"string\",\"nullable\":true,\"metadata\":{}},{\"name\":\"patient_count\",\"type\":\"integer\",\"nullable\":true,\"metadata\":{}},{\"name\":\"avg_birth_date\",\"type\":\"timestamp_ntz\",\"nullable\":true,\"metadata\":{}}]}","partitionColumns":[],"createdTime":1784315152412,"configuration":{}}}
{"add":{"path":"part-00000-f6ea7566-89f7-499e-ad04-e81f57b059ee-c000.snappy.parquet","partitionValues":{},"size":1142,"modificationTime":1784315152415,"dataChange":true,"stats":"{\"numRecords\":2,\"minValues\":{\"patient_count\":1,\"gender\":\"Female\",\"avg_birth_date\":\"1977-09-27 00:00:00\"},\"maxValues\":{\"avg_birth_date\":\"1992-11-22 00:00:00\",\"gender\":\"Male\",\"patient_count\":2},\"nullCount\":{\"avg_birth_date\":0,\"gender\":0,\"patient_count\":0}}","tags":null,"baseRowId":null,"defaultRowCommitVersion":null,"clusteringProvider":null}}